solana_proxy/__init__.py
solana_proxy/rpc/__init__.py
solana_proxy/rpc/api.py
solana_proxy/rpc/async_api.py
solana_proxy/rpc/providers/__init__.py
solana_proxy/rpc/providers/async_http.py
solana_proxy/rpc/providers/http.py
solana_proxy/rpc/providers/session.py
solana_proxy-0.1.1.dist-info/LICENSE
solana_proxy-0.1.1.dist-info/METADATA
solana_proxy-0.1.1.dist-info/WHEEL
solana_proxy-0.1.1.dist-info/RECORD
